cascade8_filename_enforcer/__init__.py
cascade8_filename_enforcer/enforcer.py
py_cascade8_filename_enforcer-0.0.3.dist-info/LICENSE
py_cascade8_filename_enforcer-0.0.3.dist-info/METADATA
py_cascade8_filename_enforcer-0.0.3.dist-info/WHEEL
py_cascade8_filename_enforcer-0.0.3.dist-info/top_level.txt
py_cascade8_filename_enforcer-0.0.3.dist-info/RECORD
