Metadata-Version: 2.1
Name: py-cascade8-filename-enforcer
Version: 0.0.3
Summary: A Python package utilizing the Cascade CMS 8 REST API to enforce file name rules, namely 1) all lowercase, 2) spaces replaced with hyphens, 3) no trailing spaces
Home-page: https://github.com/austinjhunt/CascadeCMS-filename-rule-enforcer
Author: Austin Hunt
Author-email: huntaj@cofc.edu
License: UNKNOWN
Project-URL: Bug Tracker, https://github.com/austinjhunt/CascadeCMS-filename-rule-enforcer/issues
Platform: UNKNOWN
Classifier: Programming Language :: Python :: 3
Classifier: License :: OSI Approved :: MIT License
Classifier: Operating System :: OS Independent
Requires-Python: >=3.6
Requires-Dist: requests
